EuroChannel/__init__.py
EuroChannel/audio/__init__.py
EuroChannel/video/__init__.py
test/__init__.py
EuroChannel-2023.9.1.dist-info/LICENSE.txt
EuroChannel-2023.9.1.dist-info/METADATA
EuroChannel-2023.9.1.dist-info/WHEEL
EuroChannel-2023.9.1.dist-info/top_level.txt
EuroChannel-2023.9.1.dist-info/RECORD
